pyluog/__init__.py
pyluog/test.py
pyluog-0.13.9.dist-info/LICENSE
pyluog-0.13.9.dist-info/METADATA
pyluog-0.13.9.dist-info/WHEEL
pyluog-0.13.9.dist-info/top_level.txt
pyluog-0.13.9.dist-info/RECORD
