Metadata-Version: 2.1
Name: pyluog
Version: 0.13.9
Summary: A python module for using Luogu Api.
Home-page: https://pypi.org/project/pyluog
Author: hlwdy
Author-email: hlwdyck@gmail.com
License: MIT
Platform: any
Requires-Python: >=3.6
Requires-Dist: requests
Requires-Dist: matplotlib
Requires-Dist: Pillow
